Metadata-Version: 1.0
Name: printListModulePackageAmeer
Version: 1.0.0
Summary: an API to print         a list recursively
Home-page: UNKNOWN
Author: Ameer
Author-email: ameermon.va@ignitarium.com
License: UNKNOWN
Platform: UNKNOWN
